evolutionary_keras/__init__.py
evolutionary_keras/models.py
evolutionary_keras/optimizers.py
evolutionary_keras/utilities.py
evolutionary_keras/tests/__init__.py
evolutionary_keras/tests/test_fit.py
evolutionary_keras/tests/test_utilities.py
evolutionary_keras-2.1.dist-info/LICENSE
evolutionary_keras-2.1.dist-info/METADATA
evolutionary_keras-2.1.dist-info/WHEEL
evolutionary_keras-2.1.dist-info/top_level.txt
evolutionary_keras-2.1.dist-info/RECORD
