Metadata-Version: 2.1
Name: evolutionary-keras
Version: 2.1
Summary: UNKNOWN
Home-page: https://github.com/N3PDF/evolutionary_keras
Author: S. Carrazza, J. Cruz-Martinez, Roy Stegeman
Author-email: juan.cruz@mi.infn.it, roy.stegeman@mi.infn.it
License: UNKNOWN
Platform: UNKNOWN
Classifier: Programming Language :: Python
Classifier: Topic :: Scientific/Engineering
Classifier: Topic :: Scientific/Engineering :: Physics
Classifier: Programming Language :: Python :: 3
Classifier: Programming Language :: Python :: 3.6
Requires-Python: >=3.6
Requires-Dist: numpy
Requires-Dist: cma
Requires-Dist: tensorflow (>2.1*)
Provides-Extra: docs
Requires-Dist: sphinx-rtd-theme ; extra == 'docs'
Requires-Dist: recommonmark ; extra == 'docs'
